lkcom/__init__.py
lkcom/cfgparse.py
lkcom/dataio.py
lkcom/image.py
lkcom/plot.py
lkcom/standard_func.py
lkcom/string.py
lkcom/util.py
lkcom-0.8.1.dist-info/METADATA
lkcom-0.8.1.dist-info/WHEEL
lkcom-0.8.1.dist-info/top_level.txt
lkcom-0.8.1.dist-info/RECORD
