Metadata-Version: 2.4
Name: lkcom
Version: 0.8.1
Summary: A Python library of useful routines.
Home-page: https://bitbucket.org/lukaskontenis/lkcom/
Author: Lukas Kontenis
Author-email: dse.ssd@gmail.com
Classifier: Programming Language :: Python :: 3
Classifier: License :: OSI Approved :: MIT License
Classifier: Operating System :: OS Independent
Requires-Python: >=3.6
Requires-Dist: numpy>2.0
Requires-Dist: matplotlib>=3.8.0
Requires-Dist: Pillow>=8.0.1
Requires-Dist: imageio>=2.34.2
Requires-Dist: h5py>=3.11
Dynamic: author
Dynamic: author-email
Dynamic: classifier
Dynamic: description
Dynamic: description-content-type
Dynamic: home-page
Dynamic: requires-dist
Dynamic: requires-python
Dynamic: summary
